[
  {
    "epoch": 1,
    "avg_loss": 9879369.0,
    "time_s": 6.148562669754028,
    "peak_mem_mb": 20.0087890625
  },
  {
    "epoch": 2,
    "avg_loss": 9870024.0,
    "time_s": 5.2014172077178955,
    "peak_mem_mb": 28.13720703125
  },
  {
    "epoch": 3,
    "avg_loss": 9860684.0,
    "time_s": 5.051843166351318,
    "peak_mem_mb": 28.13720703125
  },
  {
    "epoch": 4,
    "avg_loss": 9851352.0,
    "time_s": 5.231190919876099,
    "peak_mem_mb": 28.13720703125
  },
  {
    "epoch": 5,
    "avg_loss": 9842027.0,
    "time_s": 5.367932319641113,
    "peak_mem_mb": 28.13720703125
  },
  {
    "epoch": 1,
    "avg_loss": 4170900.5,
    "time_s": 6.016295433044434,
    "peak_mem_mb": 20.0087890625
  },
  {
    "epoch": 2,
    "avg_loss": 4158961.5,
    "time_s": 5.311810493469238,
    "peak_mem_mb": 28.13720703125
  },
  {
    "epoch": 3,
    "avg_loss": 4147024.75,
    "time_s": 5.12929368019104,
    "peak_mem_mb": 28.13720703125
  },
  {
    "epoch": 4,
    "avg_loss": 4135091.0,
    "time_s": 5.098113775253296,
    "peak_mem_mb": 28.13720703125
  },
  {
    "epoch": 5,
    "avg_loss": 4123159.0,
    "time_s": 5.171508312225342,
    "peak_mem_mb": 28.13720703125
  },
  {
    "epoch": 1,
    "avg_loss": 5500767.0,
    "time_s": 6.182344675064087,
    "peak_mem_mb": 20.0087890625
  },
  {
    "epoch": 2,
    "avg_loss": 5489032.5,
    "time_s": 5.044631719589233,
    "peak_mem_mb": 28.13720703125
  },
  {
    "epoch": 3,
    "avg_loss": 5477301.0,
    "time_s": 5.143856763839722,
    "peak_mem_mb": 28.13720703125
  },
  {
    "epoch": 4,
    "avg_loss": 5465571.5,
    "time_s": 4.928462505340576,
    "peak_mem_mb": 28.13720703125
  },
  {
    "epoch": 5,
    "avg_loss": 5453844.5,
    "time_s": 5.211499214172363,
    "peak_mem_mb": 28.13720703125
  },
  {
    "epoch": 1,
    "avg_loss": 5563556.5,
    "time_s": 5.763588190078735,
    "peak_mem_mb": 20.0087890625
  },
  {
    "epoch": 2,
    "avg_loss": 5555100.0,
    "time_s": 5.068893194198608,
    "peak_mem_mb": 28.13720703125
  },
  {
    "epoch": 3,
    "avg_loss": 5546656.5,
    "time_s": 4.80434513092041,
    "peak_mem_mb": 28.13720703125
  },
  {
    "epoch": 4,
    "avg_loss": 5538229.5,
    "time_s": 4.780489206314087,
    "peak_mem_mb": 28.13720703125
  },
  {
    "epoch": 5,
    "avg_loss": 5529818.0,
    "time_s": 5.040281534194946,
    "peak_mem_mb": 28.13720703125
  },
  {
    "epoch": 1,
    "avg_loss": 4.303987503051758,
    "time_s": 8.31580400466919,
    "peak_mem_mb": 20.0087890625
  },
  {
    "epoch": 2,
    "avg_loss": 4.300904273986816,
    "time_s": 6.041096925735474,
    "peak_mem_mb": 28.13720703125
  },
  {
    "epoch": 3,
    "avg_loss": 4.297825813293457,
    "time_s": 6.211711168289185,
    "peak_mem_mb": 28.13720703125
  },
  {
    "epoch": 4,
    "avg_loss": 4.2947492599487305,
    "time_s": 5.846832990646362,
    "peak_mem_mb": 28.13720703125
  },
  {
    "epoch": 5,
    "avg_loss": 4.291683197021484,
    "time_s": 6.157190322875977,
    "peak_mem_mb": 28.13720703125
  },
  {
    "epoch": 1,
    "avg_loss": 4.367314338684082,
    "time_s": 6.848129510879517,
    "peak_mem_mb": 20.0087890625
  },
  {
    "epoch": 2,
    "avg_loss": 4.364741325378418,
    "time_s": 5.7206807136535645,
    "peak_mem_mb": 28.13720703125
  },
  {
    "epoch": 3,
    "avg_loss": 4.362175464630127,
    "time_s": 5.751077651977539,
    "peak_mem_mb": 28.13720703125
  },
  {
    "epoch": 4,
    "avg_loss": 4.359609603881836,
    "time_s": 5.815275430679321,
    "peak_mem_mb": 28.13720703125
  },
  {
    "epoch": 5,
    "avg_loss": 4.3570404052734375,
    "time_s": 5.79108738899231,
    "peak_mem_mb": 28.13720703125
  },
  {
    "epoch": 1,
    "avg_loss": 4.132760047912598,
    "time_s": 6.90131139755249,
    "peak_mem_mb": 20.0087890625
  },
  {
    "epoch": 2,
    "avg_loss": 4.127740859985352,
    "time_s": 5.8492467403411865,
    "peak_mem_mb": 28.13720703125
  },
  {
    "epoch": 3,
    "avg_loss": 4.12277889251709,
    "time_s": 5.992393732070923,
    "peak_mem_mb": 28.13720703125
  },
  {
    "epoch": 4,
    "avg_loss": 4.117875099182129,
    "time_s": 5.928777694702148,
    "peak_mem_mb": 28.13720703125
  },
  {
    "epoch": 5,
    "avg_loss": 4.112878799438477,
    "time_s": 5.921475172042847,
    "peak_mem_mb": 28.13720703125
  },
  {
    "epoch": 6,
    "avg_loss": 4.107578754425049,
    "time_s": 6.037152528762817,
    "peak_mem_mb": 28.13720703125
  },
  {
    "epoch": 7,
    "avg_loss": 4.102330207824707,
    "time_s": 5.8972697257995605,
    "peak_mem_mb": 28.13720703125
  },
  {
    "epoch": 8,
    "avg_loss": 4.097136497497559,
    "time_s": 6.042942047119141,
    "peak_mem_mb": 28.13720703125
  },
  {
    "epoch": 9,
    "avg_loss": 4.092006683349609,
    "time_s": 5.872387170791626,
    "peak_mem_mb": 28.13720703125
  },
  {
    "epoch": 10,
    "avg_loss": 4.086945533752441,
    "time_s": 5.886367321014404,
    "peak_mem_mb": 28.13720703125
  },
  {
    "epoch": 11,
    "avg_loss": 4.08195686340332,
    "time_s": 5.856715679168701,
    "peak_mem_mb": 28.13720703125
  },
  {
    "epoch": 12,
    "avg_loss": 4.0770463943481445,
    "time_s": 5.922076225280762,
    "peak_mem_mb": 28.13720703125
  },
  {
    "epoch": 13,
    "avg_loss": 4.072185039520264,
    "time_s": 5.963189125061035,
    "peak_mem_mb": 28.13720703125
  },
  {
    "epoch": 14,
    "avg_loss": 4.067360877990723,
    "time_s": 5.867927312850952,
    "peak_mem_mb": 28.13720703125
  },
  {
    "epoch": 15,
    "avg_loss": 4.06231689453125,
    "time_s": 5.912078857421875,
    "peak_mem_mb": 28.13720703125
  },
  {
    "epoch": 16,
    "avg_loss": 4.0571699142456055,
    "time_s": 5.78964376449585,
    "peak_mem_mb": 28.13720703125
  },
  {
    "epoch": 17,
    "avg_loss": 4.052027702331543,
    "time_s": 5.845701456069946,
    "peak_mem_mb": 28.13720703125
  },
  {
    "epoch": 18,
    "avg_loss": 4.046953201293945,
    "time_s": 5.910428285598755,
    "peak_mem_mb": 28.13720703125
  },
  {
    "epoch": 19,
    "avg_loss": 4.0419487953186035,
    "time_s": 5.883857011795044,
    "peak_mem_mb": 28.13720703125
  },
  {
    "epoch": 20,
    "avg_loss": 4.037027359008789,
    "time_s": 5.939967393875122,
    "peak_mem_mb": 28.13720703125
  },
  {
    "epoch": 21,
    "avg_loss": 4.032187461853027,
    "time_s": 6.052689790725708,
    "peak_mem_mb": 28.13720703125
  },
  {
    "epoch": 22,
    "avg_loss": 4.027435302734375,
    "time_s": 5.879357099533081,
    "peak_mem_mb": 28.13720703125
  },
  {
    "epoch": 23,
    "avg_loss": 4.022556781768799,
    "time_s": 5.883728504180908,
    "peak_mem_mb": 28.13720703125
  },
  {
    "epoch": 24,
    "avg_loss": 4.017646312713623,
    "time_s": 5.850285053253174,
    "peak_mem_mb": 28.13720703125
  },
  {
    "epoch": 25,
    "avg_loss": 4.012813568115234,
    "time_s": 5.9206531047821045,
    "peak_mem_mb": 28.13720703125
  },
  {
    "epoch": 26,
    "avg_loss": 4.008062362670898,
    "time_s": 5.9068217277526855,
    "peak_mem_mb": 28.13720703125
  },
  {
    "epoch": 27,
    "avg_loss": 4.003398895263672,
    "time_s": 5.951131582260132,
    "peak_mem_mb": 28.13720703125
  },
  {
    "epoch": 28,
    "avg_loss": 3.998818874359131,
    "time_s": 5.966398477554321,
    "peak_mem_mb": 28.13720703125
  },
  {
    "epoch": 29,
    "avg_loss": 3.9943318367004395,
    "time_s": 5.868764638900757,
    "peak_mem_mb": 28.13720703125
  },
  {
    "epoch": 30,
    "avg_loss": 3.9899373054504395,
    "time_s": 6.136044502258301,
    "peak_mem_mb": 28.13720703125
  },
  {
    "epoch": 31,
    "avg_loss": 3.9856364727020264,
    "time_s": 5.9955010414123535,
    "peak_mem_mb": 28.13720703125
  },
  {
    "epoch": 32,
    "avg_loss": 3.9814319610595703,
    "time_s": 5.86366868019104,
    "peak_mem_mb": 28.13720703125
  },
  {
    "epoch": 33,
    "avg_loss": 3.9773221015930176,
    "time_s": 5.9391491413116455,
    "peak_mem_mb": 28.13720703125
  },
  {
    "epoch": 34,
    "avg_loss": 3.97330904006958,
    "time_s": 5.87596869468689,
    "peak_mem_mb": 28.13720703125
  },
  {
    "epoch": 35,
    "avg_loss": 3.9693922996520996,
    "time_s": 5.937625885009766,
    "peak_mem_mb": 28.13720703125
  },
  {
    "epoch": 36,
    "avg_loss": 3.965360403060913,
    "time_s": 5.866003513336182,
    "peak_mem_mb": 28.13720703125
  },
  {
    "epoch": 37,
    "avg_loss": 3.9611642360687256,
    "time_s": 5.943607807159424,
    "peak_mem_mb": 28.13720703125
  },
  {
    "epoch": 38,
    "avg_loss": 3.9570388793945312,
    "time_s": 5.920058012008667,
    "peak_mem_mb": 28.13720703125
  },
  {
    "epoch": 39,
    "avg_loss": 3.952986240386963,
    "time_s": 6.158175945281982,
    "peak_mem_mb": 28.13720703125
  },
  {
    "epoch": 1,
    "avg_loss": 4.278580665588379,
    "time_s": 6.7974560260772705,
    "peak_mem_mb": 20.0087890625
  },
  {
    "epoch": 2,
    "avg_loss": 4.272538185119629,
    "time_s": 5.900097846984863,
    "peak_mem_mb": 28.13720703125
  },
  {
    "epoch": 3,
    "avg_loss": 4.266672611236572,
    "time_s": 5.883899688720703,
    "peak_mem_mb": 28.13720703125
  },
  {
    "epoch": 1,
    "avg_loss": 4.293710708618164,
    "time_s": 8.446774244308472,
    "peak_mem_mb": 20.0087890625
  },
  {
    "epoch": 2,
    "avg_loss": 4.290132999420166,
    "time_s": 6.317361116409302,
    "peak_mem_mb": 28.13720703125
  },
  {
    "epoch": 3,
    "avg_loss": 4.286563873291016,
    "time_s": 6.115674734115601,
    "peak_mem_mb": 28.13720703125
  },
  {
    "epoch": 1,
    "avg_loss": 4.20863151550293,
    "time_s": 6.9563727378845215,
    "peak_mem_mb": 20.0087890625
  },
  {
    "epoch": 2,
    "avg_loss": 4.206407070159912,
    "time_s": 5.91126012802124,
    "peak_mem_mb": 28.13720703125
  },
  {
    "epoch": 3,
    "avg_loss": 4.204187393188477,
    "time_s": 5.989705324172974,
    "peak_mem_mb": 28.13720703125
  },
  {
    "epoch": 1,
    "avg_loss": 4.693367004394531,
    "time_s": 7.112835168838501,
    "peak_mem_mb": 20.0087890625
  },
  {
    "epoch": 2,
    "avg_loss": 4.689759254455566,
    "time_s": 5.925922155380249,
    "peak_mem_mb": 28.13720703125
  },
  {
    "epoch": 3,
    "avg_loss": 4.685968399047852,
    "time_s": 6.124441385269165,
    "peak_mem_mb": 28.13720703125
  },
  {
    "epoch": 1,
    "avg_loss": 4.302921295166016,
    "time_s": 7.145509719848633,
    "peak_mem_mb": 20.0087890625
  },
  {
    "epoch": 2,
    "avg_loss": 4.300173282623291,
    "time_s": 5.858030080795288,
    "peak_mem_mb": 28.13720703125
  },
  {
    "epoch": 3,
    "avg_loss": 4.2974324226379395,
    "time_s": 5.916959524154663,
    "peak_mem_mb": 28.13720703125
  },
  {
    "epoch": 1,
    "avg_loss": 4.302921295166016,
    "time_s": 6.806447267532349,
    "peak_mem_mb": 20.0087890625
  },
  {
    "epoch": 2,
    "avg_loss": 4.300173282623291,
    "time_s": 5.904533863067627,
    "peak_mem_mb": 28.13720703125
  },
  {
    "epoch": 3,
    "avg_loss": 4.2974324226379395,
    "time_s": 6.106265306472778,
    "peak_mem_mb": 28.13720703125
  },
  {
    "epoch": 1,
    "avg_loss": 4.302921295166016,
    "time_s": 7.705989837646484,
    "peak_mem_mb": 20.0087890625
  },
  {
    "epoch": 2,
    "avg_loss": 4.300173282623291,
    "time_s": 6.191879987716675,
    "peak_mem_mb": 28.13720703125
  },
  {
    "epoch": 3,
    "avg_loss": 4.2974324226379395,
    "time_s": 6.030645847320557,
    "peak_mem_mb": 28.13720703125
  },
  {
    "epoch": 1,
    "avg_loss": 4.302921295166016,
    "time_s": 7.130220890045166,
    "peak_mem_mb": 20.0087890625
  },
  {
    "epoch": 2,
    "avg_loss": 4.300173282623291,
    "time_s": 5.957360744476318,
    "peak_mem_mb": 28.13720703125
  },
  {
    "epoch": 3,
    "avg_loss": 4.2974324226379395,
    "time_s": 5.845787286758423,
    "peak_mem_mb": 28.13720703125
  },
  {
    "epoch": 1,
    "avg_loss": 4.302921295166016,
    "time_s": 6.816164970397949,
    "peak_mem_mb": 20.0087890625
  },
  {
    "epoch": 2,
    "avg_loss": 4.300173282623291,
    "time_s": 6.052160263061523,
    "peak_mem_mb": 28.13720703125
  },
  {
    "epoch": 3,
    "avg_loss": 4.2974324226379395,
    "time_s": 5.9000303745269775,
    "peak_mem_mb": 28.13720703125
  },
  {
    "epoch": 4,
    "avg_loss": 4.294698715209961,
    "time_s": 5.824117422103882,
    "peak_mem_mb": 28.13720703125
  },
  {
    "epoch": 5,
    "avg_loss": 4.291974067687988,
    "time_s": 5.9638752937316895,
    "peak_mem_mb": 28.13720703125
  },
  {
    "epoch": 1,
    "avg_loss": 4.302921295166016,
    "time_s": 10.00281310081482,
    "peak_mem_mb": 20.0087890625
  },
  {
    "epoch": 2,
    "avg_loss": 4.300173282623291,
    "time_s": 8.145787477493286,
    "peak_mem_mb": 28.13720703125
  },
  {
    "epoch": 3,
    "avg_loss": 4.2974324226379395,
    "time_s": 7.603522062301636,
    "peak_mem_mb": 28.13720703125
  },
  {
    "epoch": 4,
    "avg_loss": 4.294698715209961,
    "time_s": 7.783249139785767,
    "peak_mem_mb": 28.13720703125
  },
  {
    "epoch": 5,
    "avg_loss": 4.291974067687988,
    "time_s": 7.3319456577301025,
    "peak_mem_mb": 28.13720703125
  },
  {
    "epoch": 1,
    "avg_loss": 4.302921295166016,
    "time_s": 9.781013250350952,
    "peak_mem_mb": 20.0087890625
  },
  {
    "epoch": 2,
    "avg_loss": 4.300173282623291,
    "time_s": 7.736126899719238,
    "peak_mem_mb": 28.13720703125
  },
  {
    "epoch": 3,
    "avg_loss": 4.2974324226379395,
    "time_s": 6.824427366256714,
    "peak_mem_mb": 28.13720703125
  },
  {
    "epoch": 4,
    "avg_loss": 4.294698715209961,
    "time_s": 6.885141372680664,
    "peak_mem_mb": 28.13720703125
  },
  {
    "epoch": 5,
    "avg_loss": 4.291974067687988,
    "time_s": 6.85030460357666,
    "peak_mem_mb": 28.13720703125
  },
  {
    "epoch": 1,
    "avg_loss": 4.302921295166016,
    "time_s": 8.243943691253662,
    "peak_mem_mb": 20.0087890625
  },
  {
    "epoch": 2,
    "avg_loss": 4.300173282623291,
    "time_s": 6.299204587936401,
    "peak_mem_mb": 28.13720703125
  },
  {
    "epoch": 3,
    "avg_loss": 4.2974324226379395,
    "time_s": 6.1652138233184814,
    "peak_mem_mb": 28.13720703125
  },
  {
    "epoch": 4,
    "avg_loss": 4.294698715209961,
    "time_s": 6.336809158325195,
    "peak_mem_mb": 28.13720703125
  },
  {
    "epoch": 5,
    "avg_loss": 4.291974067687988,
    "time_s": 6.141340494155884,
    "peak_mem_mb": 28.13720703125
  },
  {
    "epoch": 6,
    "avg_loss": 4.28925895690918,
    "time_s": 6.35262656211853,
    "peak_mem_mb": 28.13720703125
  },
  {
    "epoch": 7,
    "avg_loss": 4.286550045013428,
    "time_s": 6.333063125610352,
    "peak_mem_mb": 28.13720703125
  },
  {
    "epoch": 8,
    "avg_loss": 4.283851146697998,
    "time_s": 6.315547227859497,
    "peak_mem_mb": 28.13720703125
  },
  {
    "epoch": 9,
    "avg_loss": 4.281160354614258,
    "time_s": 6.210314512252808,
    "peak_mem_mb": 28.13720703125
  },
  {
    "epoch": 10,
    "avg_loss": 4.278477668762207,
    "time_s": 6.443706512451172,
    "peak_mem_mb": 28.13720703125
  },
  {
    "epoch": 11,
    "avg_loss": 4.2758026123046875,
    "time_s": 6.753492832183838,
    "peak_mem_mb": 28.13720703125
  },
  {
    "epoch": 12,
    "avg_loss": 4.273135662078857,
    "time_s": 6.482144594192505,
    "peak_mem_mb": 28.13720703125
  },
  {
    "epoch": 13,
    "avg_loss": 4.270477294921875,
    "time_s": 6.511472225189209,
    "peak_mem_mb": 28.13720703125
  },
  {
    "epoch": 14,
    "avg_loss": 4.267824172973633,
    "time_s": 6.209002494812012,
    "peak_mem_mb": 28.13720703125
  },
  {
    "epoch": 15,
    "avg_loss": 4.265179634094238,
    "time_s": 6.154110908508301,
    "peak_mem_mb": 28.13720703125
  },
  {
    "epoch": 16,
    "avg_loss": 4.262540817260742,
    "time_s": 6.222323894500732,
    "peak_mem_mb": 28.13720703125
  },
  {
    "epoch": 17,
    "avg_loss": 4.259906768798828,
    "time_s": 6.227902412414551,
    "peak_mem_mb": 28.13720703125
  },
  {
    "epoch": 18,
    "avg_loss": 4.257280349731445,
    "time_s": 6.2808732986450195,
    "peak_mem_mb": 28.13720703125
  },
  {
    "epoch": 19,
    "avg_loss": 4.254659652709961,
    "time_s": 6.310272455215454,
    "peak_mem_mb": 28.13720703125
  },
  {
    "epoch": 20,
    "avg_loss": 4.252057075500488,
    "time_s": 6.1133153438568115,
    "peak_mem_mb": 28.13720703125
  },
  {
    "epoch": 21,
    "avg_loss": 4.249459266662598,
    "time_s": 6.149147033691406,
    "peak_mem_mb": 28.13720703125
  },
  {
    "epoch": 22,
    "avg_loss": 4.246868133544922,
    "time_s": 6.217920541763306,
    "peak_mem_mb": 28.13720703125
  },
  {
    "epoch": 23,
    "avg_loss": 4.244280815124512,
    "time_s": 6.206676959991455,
    "peak_mem_mb": 28.13720703125
  },
  {
    "epoch": 24,
    "avg_loss": 4.241699695587158,
    "time_s": 6.2022788524627686,
    "peak_mem_mb": 28.13720703125
  },
  {
    "epoch": 25,
    "avg_loss": 4.239108085632324,
    "time_s": 6.312196254730225,
    "peak_mem_mb": 28.13720703125
  },
  {
    "epoch": 26,
    "avg_loss": 4.236514568328857,
    "time_s": 6.232377767562866,
    "peak_mem_mb": 28.13720703125
  },
  {
    "epoch": 27,
    "avg_loss": 4.233922958374023,
    "time_s": 6.2501795291900635,
    "peak_mem_mb": 28.13720703125
  },
  {
    "epoch": 28,
    "avg_loss": 4.2313337326049805,
    "time_s": 6.3331029415130615,
    "peak_mem_mb": 28.13720703125
  },
  {
    "epoch": 29,
    "avg_loss": 4.2287468910217285,
    "time_s": 6.281138896942139,
    "peak_mem_mb": 28.13720703125
  },
  {
    "epoch": 30,
    "avg_loss": 4.226163864135742,
    "time_s": 6.247737407684326,
    "peak_mem_mb": 28.13720703125
  },
  {
    "epoch": 31,
    "avg_loss": 4.223584175109863,
    "time_s": 6.327608346939087,
    "peak_mem_mb": 28.13720703125
  },
  {
    "epoch": 32,
    "avg_loss": 4.22100830078125,
    "time_s": 6.226153373718262,
    "peak_mem_mb": 28.13720703125
  },
  {
    "epoch": 33,
    "avg_loss": 4.2184343338012695,
    "time_s": 6.192979335784912,
    "peak_mem_mb": 28.13720703125
  },
  {
    "epoch": 34,
    "avg_loss": 4.215865135192871,
    "time_s": 6.221745491027832,
    "peak_mem_mb": 28.13720703125
  },
  {
    "epoch": 35,
    "avg_loss": 4.213298797607422,
    "time_s": 6.252822399139404,
    "peak_mem_mb": 28.13720703125
  },
  {
    "epoch": 36,
    "avg_loss": 4.21073579788208,
    "time_s": 6.2276225090026855,
    "peak_mem_mb": 28.13720703125
  },
  {
    "epoch": 37,
    "avg_loss": 4.208176612854004,
    "time_s": 6.387808799743652,
    "peak_mem_mb": 28.13720703125
  },
  {
    "epoch": 38,
    "avg_loss": 4.205620765686035,
    "time_s": 6.2120184898376465,
    "peak_mem_mb": 28.13720703125
  },
  {
    "epoch": 39,
    "avg_loss": 4.203067779541016,
    "time_s": 6.275812864303589,
    "peak_mem_mb": 28.13720703125
  },
  {
    "epoch": 40,
    "avg_loss": 4.200545310974121,
    "time_s": 6.176197052001953,
    "peak_mem_mb": 28.13720703125
  },
  {
    "epoch": 41,
    "avg_loss": 4.198042869567871,
    "time_s": 6.224805116653442,
    "peak_mem_mb": 28.13720703125
  },
  {
    "epoch": 42,
    "avg_loss": 4.195590972900391,
    "time_s": 6.2584662437438965,
    "peak_mem_mb": 28.13720703125
  },
  {
    "epoch": 43,
    "avg_loss": 4.193148612976074,
    "time_s": 6.1987080574035645,
    "peak_mem_mb": 28.13720703125
  },
  {
    "epoch": 44,
    "avg_loss": 4.190672874450684,
    "time_s": 6.258647441864014,
    "peak_mem_mb": 28.13720703125
  },
  {
    "epoch": 45,
    "avg_loss": 4.188218593597412,
    "time_s": 6.4042809009552,
    "peak_mem_mb": 28.13720703125
  },
  {
    "epoch": 46,
    "avg_loss": 4.185834884643555,
    "time_s": 6.1873815059661865,
    "peak_mem_mb": 28.13720703125
  },
  {
    "epoch": 47,
    "avg_loss": 4.183448314666748,
    "time_s": 6.16408109664917,
    "peak_mem_mb": 28.13720703125
  },
  {
    "epoch": 48,
    "avg_loss": 4.181055068969727,
    "time_s": 6.123708248138428,
    "peak_mem_mb": 28.13720703125
  },
  {
    "epoch": 49,
    "avg_loss": 4.178658962249756,
    "time_s": 6.254232168197632,
    "peak_mem_mb": 28.13720703125
  },
  {
    "epoch": 1,
    "avg_loss": 4.0010457038879395,
    "time_s": 9.202574253082275,
    "peak_mem_mb": 1248.2275390625
  },
  {
    "epoch": 2,
    "avg_loss": 3.8207881450653076,
    "time_s": 7.876215934753418,
    "peak_mem_mb": 1292.2880859375
  },
  {
    "epoch": 3,
    "avg_loss": 3.061936378479004,
    "time_s": 7.514011383056641,
    "peak_mem_mb": 1292.2880859375
  },
  {
    "epoch": 4,
    "avg_loss": 2.5354421138763428,
    "time_s": 7.512750148773193,
    "peak_mem_mb": 1291.9052734375
  },
  {
    "epoch": 5,
    "avg_loss": 2.2202205657958984,
    "time_s": 7.745100975036621,
    "peak_mem_mb": 1292.3818359375
  },
  {
    "epoch": 6,
    "avg_loss": 2.0086731910705566,
    "time_s": 7.644052982330322,
    "peak_mem_mb": 1292.3818359375
  },
  {
    "epoch": 7,
    "avg_loss": 1.8938992023468018,
    "time_s": 7.5008838176727295,
    "peak_mem_mb": 1292.3818359375
  },
  {
    "epoch": 8,
    "avg_loss": 1.7815742492675781,
    "time_s": 7.600907325744629,
    "peak_mem_mb": 1292.3818359375
  },
  {
    "epoch": 9,
    "avg_loss": 1.7080483436584473,
    "time_s": 7.546803951263428,
    "peak_mem_mb": 1292.3818359375
  }
]